exception_logger/__init__.py
exception_logger/app.py
exception_logger/config.py
exception_logger/models.py
exception_logger-0.2.dist-info/METADATA
exception_logger-0.2.dist-info/WHEEL
exception_logger-0.2.dist-info/top_level.txt
exception_logger-0.2.dist-info/RECORD
