Metadata-Version: 2.1
Name: exception-logger
Version: 0.2
Requires-Dist: Flask
Requires-Dist: mysql-connector-python
